[
  {
    "libraryId": "generated",
    "id": "BzY8BHdnJy",
    "componentId": "RuLJJhsLkK",
    "name": "Name",
    "description": "",
    "status": "published",
    "orderIdx": "03qKK",
    "revision": 17,
    "model": "",
    "view": "<style data-format-version=\"30\">/* Type: grid Id: custom-grid Title: Custom grid Instance Id: BMgDPUl8nx */ .-grid--custom[data-instance-id=\"BMgDPUl8nx\"]:not(._._._._._._#_) { ---self--display: grid; display: var(---self--display); grid-template-rows: minmax(36px,36px) minmax(36px,36px) minmax(36px,36px) minmax(36px,36px) minmax(36px, auto); grid-template-columns: minmax(0px,1fr) minmax(0px,1fr) minmax(0px,1fr) minmax(0px,1fr) minmax(0px,1fr) minmax(0px,1fr) minmax(0px,1fr) minmax(0px,1fr) minmax(0px,1fr) minmax(0px,1fr) minmax(0px,1fr) minmax(0px,1fr); row-gap: var(---spacing--row-gap); column-gap: var(---spacing--column-gap); } .-grid--custom[data-instance-id=\"BMgDPUl8nx\"] > :nth-child(1):not(._._._._._._#_) { grid-column: 1; grid-column-end: 13; grid-row: 1; grid-row-end: 6; order: 0; position: relative; } /* Data: {\"type\":\"grid\",\"details\":{\"title\":\"Custom grid\",\"description\":\"\",\"id\":\"custom-grid\",\"exampleContent\":null,\"slug\":\"custom\",\"isInternal\":true,\"isHidden\":true,\"instanceId\":\"BMgDPUl8nx\"},\"props\":{\"columns\":[{\"min\":{\"value\":0,\"unit\":\"px\"},\"max\":{\"value\":1,\"unit\":\"fr\"}},{\"min\":{\"value\":0,\"unit\":\"px\"},\"max\":{\"value\":1,\"unit\":\"fr\"}},{\"min\":{\"value\":0,\"unit\":\"px\"},\"max\":{\"value\":1,\"unit\":\"fr\"}},{\"min\":{\"value\":0,\"unit\":\"px\"},\"max\":{\"value\":1,\"unit\":\"fr\"}},{\"min\":{\"value\":0,\"unit\":\"px\"},\"max\":{\"value\":1,\"unit\":\"fr\"}},{\"min\":{\"value\":0,\"unit\":\"px\"},\"max\":{\"value\":1,\"unit\":\"fr\"}},{\"min\":{\"value\":0,\"unit\":\"px\"},\"max\":{\"value\":1,\"unit\":\"fr\"}},{\"min\":{\"value\":0,\"unit\":\"px\"},\"max\":{\"value\":1,\"unit\":\"fr\"}},{\"min\":{\"value\":0,\"unit\":\"px\"},\"max\":{\"value\":1,\"unit\":\"fr\"}},{\"min\":{\"value\":0,\"unit\":\"px\"},\"max\":{\"value\":1,\"unit\":\"fr\"}},{\"min\":{\"value\":0,\"unit\":\"px\"},\"max\":{\"value\":1,\"unit\":\"fr\"}},{\"min\":{\"value\":0,\"unit\":\"px\"},\"max\":{\"value\":1,\"unit\":\"fr\"}}],\"rows\":[{\"min\":{\"value\":36,\"unit\":\"px\"},\"max\":{\"value\":36,\"unit\":\"px\"}},{\"min\":{\"value\":36,\"unit\":\"px\"},\"max\":{\"value\":36,\"unit\":\"px\"}},{\"min\":{\"value\":36,\"unit\":\"px\"},\"max\":{\"value\":36,\"unit\":\"px\"}},{\"min\":{\"value\":36,\"unit\":\"px\"},\"max\":{\"value\":36,\"unit\":\"px\"}},{\"min\":{\"value\":36,\"unit\":\"px\"},\"max\":null}],\"items\":[{\"from\":{\"row\":1,\"column\":1},\"to\":{\"row\":6,\"column\":13},\"order\":0}]}} */ /* --- */  /* Type: media Id: gzFMf4-iN9 Instance Id: U0gNOb557K */ .-media--[data-instance-id=\"U0gNOb557K\"][class*=\"-block--media\"]:not(._._._._._._#_) { width: 100%; } .-media--[data-instance-id=\"U0gNOb557K\"] > picture:not(._._._._._._#_) { position: relative; overflow: hidden; height: auto; } .-media--[data-instance-id=\"U0gNOb557K\"] > picture > img:not(._._._._._._#_) { object-fit: cover; object-position: 50% 50%; } /* Data: {\"type\":\"media\",\"details\":{\"title\":\"\",\"description\":\"\",\"id\":\"gzFMf4-iN9\",\"exampleContent\":null,\"instanceId\":\"U0gNOb557K\"},\"props\":{\"width\":{\"value\":100,\"unit\":\"%\"},\"height\":null,\"objectFit\":\"cover\",\"objectPositionX\":{\"value\":50,\"unit\":\"%\"},\"objectPositionY\":{\"value\":50,\"unit\":\"%\"}}} */ /* --- */  /* Type: spacing Id: GR8D2zPSUp Instance Id: U0gNOb557K */ .-spacing--[data-instance-id=\"U0gNOb557K\"]:not(._._._._._._#_) { padding-top: 0px; padding-right: 0px; padding-bottom: 0px; padding-left: 0px; ---spacing--row-gap: 0px; ---spacing--column-gap: 0px; } .-spacing--[data-instance-id=\"U0gNOb557K\"] > *:not(._._._._._._#_) { ---layout--row-gap: 0px; ---layout--column-gap: 0px; } /* Data: {\"type\":\"spacing\",\"details\":{\"title\":\"\",\"description\":\"\",\"id\":\"GR8D2zPSUp\",\"exampleContent\":null,\"instanceId\":\"U0gNOb557K\"},\"props\":{\"paddingTop\":{\"value\":0,\"unit\":\"px\"},\"paddingBottom\":{\"value\":0,\"unit\":\"px\"},\"paddingLeft\":{\"value\":0,\"unit\":\"px\"},\"paddingRight\":{\"value\":0,\"unit\":\"px\"},\"rowGap\":{\"value\":0,\"unit\":\"px\"},\"columnGap\":{\"value\":0,\"unit\":\"px\"}}} */ /* --- */  /* Type: spacing Id: 1Pbz5auvuy Title: Large section Instance Id: BMgDPUl8nx */ .-spacing--large-section[data-instance-id=\"BMgDPUl8nx\"]:not(._._._._._._#_) { padding-top: 8px; padding-right: 100px; padding-bottom: 8px; padding-left: 100px; ---spacing--row-gap: 12px; ---spacing--column-gap: 12px; } .-spacing--large-section[data-instance-id=\"BMgDPUl8nx\"] > *:not(._._._._._._#_) { ---layout--row-gap: 12px; ---layout--column-gap: 12px; } /* Data: {\"type\":\"spacing\",\"details\":{\"title\":\"Large section\",\"description\":\"\",\"id\":\"1Pbz5auvuy\",\"exampleContent\":null,\"slug\":\"large-section\",\"collectionId\":\"9zpuzADm9w\",\"instanceId\":\"BMgDPUl8nx\"},\"props\":{\"paddingTop\":{\"value\":8,\"unit\":\"px\"},\"paddingBottom\":{\"value\":8,\"unit\":\"px\"},\"paddingLeft\":{\"value\":100,\"unit\":\"px\"},\"paddingRight\":{\"value\":100,\"unit\":\"px\"},\"rowGap\":{\"value\":12,\"unit\":\"px\"},\"columnGap\":{\"value\":12,\"unit\":\"px\"}}} */ /* --- */  /* Type: dimensions Id: MeLzpwe4xn Instance Id: BMgDPUl8nx */ .-dimensions--[data-instance-id=\"BMgDPUl8nx\"]:not(._._._._._._#_) { max-width: min(var(---self--max-available-width, 100%), var(---self--max-width, 100%)); } /* Data: {\"type\":\"dimensions\",\"details\":{\"title\":\"\",\"description\":\"\",\"id\":\"MeLzpwe4xn\",\"exampleContent\":null,\"instanceId\":\"BMgDPUl8nx\"},\"props\":{\"minWidth\":null,\"maxWidth\":null,\"minHeight\":null,\"maxHeight\":null}} */</style><section class=\"-dimensions-- -grid--custom -spacing--large-section\" data-instance-id=\"BMgDPUl8nx\"><div class=\"-block--media -media-- -spacing--\" data-instance-id=\"U0gNOb557K\"><picture class=\"-image--foreground\"><img src=\"https://feaas.blob.core.windows.net/images/w5KOvtvgQFSL2hiaZ5mpxwSam-fgnb9D.png\" /></picture></div></section>",
    "diff": {},
    "breakpointIds": null,
    "datasourceIds": [],
    "isEmbeddable": false,
    "forkOriginId": null,
    "forkOriginRevision": 0,
    "forkedAt": null,
    "classList": [
      "-theme--default"
    ],
    "createdAt": "2024-06-26T03:10:54.728Z",
    "deletedAt": null,
    "modifiedAt": "2024-06-26T03:20:40.119Z",
    "modifiedBy": {
      "id": "63f775b550477258a136da0e",
      "name": "Christopher Haddad",
      "givenName": "Christopher",
      "familyName": "Haddad",
      "email": "chris.haddad@sitecore.com",
      "picture": "https://s.gravatar.com/avatar/a9f8fbaf23e64731b5291cfa9e8749d4?s=480&r=pg&d=https%3A%2F%2Fcdn.auth0.com%2Favatars%2Fch.png"
    }
  },
  {
    "libraryId": "generated",
    "id": "BzY8BHdnJy",
    "componentId": "RuLJJhsLkK",
    "name": "Name",
    "description": "",
    "status": "staged",
    "orderIdx": "03qKK",
    "revision": 17,
    "model": "",
    "view": "<style data-format-version=\"30\">/* Type: grid Id: custom-grid Title: Custom grid Instance Id: BMgDPUl8nx */ .-grid--custom[data-instance-id=\"BMgDPUl8nx\"]:not(._._._._._._#_) { ---self--display: grid; display: var(---self--display); grid-template-rows: minmax(36px,36px) minmax(36px,36px) minmax(36px,36px) minmax(36px,36px) minmax(36px, auto); grid-template-columns: minmax(0px,1fr) minmax(0px,1fr) minmax(0px,1fr) minmax(0px,1fr) minmax(0px,1fr) minmax(0px,1fr) minmax(0px,1fr) minmax(0px,1fr) minmax(0px,1fr) minmax(0px,1fr) minmax(0px,1fr) minmax(0px,1fr); row-gap: var(---spacing--row-gap); column-gap: var(---spacing--column-gap); } .-grid--custom[data-instance-id=\"BMgDPUl8nx\"] > :nth-child(1):not(._._._._._._#_) { grid-column: 1; grid-column-end: 13; grid-row: 1; grid-row-end: 6; order: 0; position: relative; } /* Data: {\"type\":\"grid\",\"details\":{\"title\":\"Custom grid\",\"description\":\"\",\"id\":\"custom-grid\",\"exampleContent\":null,\"slug\":\"custom\",\"isInternal\":true,\"isHidden\":true,\"instanceId\":\"BMgDPUl8nx\"},\"props\":{\"columns\":[{\"min\":{\"value\":0,\"unit\":\"px\"},\"max\":{\"value\":1,\"unit\":\"fr\"}},{\"min\":{\"value\":0,\"unit\":\"px\"},\"max\":{\"value\":1,\"unit\":\"fr\"}},{\"min\":{\"value\":0,\"unit\":\"px\"},\"max\":{\"value\":1,\"unit\":\"fr\"}},{\"min\":{\"value\":0,\"unit\":\"px\"},\"max\":{\"value\":1,\"unit\":\"fr\"}},{\"min\":{\"value\":0,\"unit\":\"px\"},\"max\":{\"value\":1,\"unit\":\"fr\"}},{\"min\":{\"value\":0,\"unit\":\"px\"},\"max\":{\"value\":1,\"unit\":\"fr\"}},{\"min\":{\"value\":0,\"unit\":\"px\"},\"max\":{\"value\":1,\"unit\":\"fr\"}},{\"min\":{\"value\":0,\"unit\":\"px\"},\"max\":{\"value\":1,\"unit\":\"fr\"}},{\"min\":{\"value\":0,\"unit\":\"px\"},\"max\":{\"value\":1,\"unit\":\"fr\"}},{\"min\":{\"value\":0,\"unit\":\"px\"},\"max\":{\"value\":1,\"unit\":\"fr\"}},{\"min\":{\"value\":0,\"unit\":\"px\"},\"max\":{\"value\":1,\"unit\":\"fr\"}},{\"min\":{\"value\":0,\"unit\":\"px\"},\"max\":{\"value\":1,\"unit\":\"fr\"}}],\"rows\":[{\"min\":{\"value\":36,\"unit\":\"px\"},\"max\":{\"value\":36,\"unit\":\"px\"}},{\"min\":{\"value\":36,\"unit\":\"px\"},\"max\":{\"value\":36,\"unit\":\"px\"}},{\"min\":{\"value\":36,\"unit\":\"px\"},\"max\":{\"value\":36,\"unit\":\"px\"}},{\"min\":{\"value\":36,\"unit\":\"px\"},\"max\":{\"value\":36,\"unit\":\"px\"}},{\"min\":{\"value\":36,\"unit\":\"px\"},\"max\":null}],\"items\":[{\"from\":{\"row\":1,\"column\":1},\"to\":{\"row\":6,\"column\":13},\"order\":0}]}} */ /* --- */  /* Type: media Id: gzFMf4-iN9 Instance Id: U0gNOb557K */ .-media--[data-instance-id=\"U0gNOb557K\"][class*=\"-block--media\"]:not(._._._._._._#_) { width: 100%; } .-media--[data-instance-id=\"U0gNOb557K\"] > picture:not(._._._._._._#_) { position: relative; overflow: hidden; height: auto; } .-media--[data-instance-id=\"U0gNOb557K\"] > picture > img:not(._._._._._._#_) { object-fit: cover; object-position: 50% 50%; } /* Data: {\"type\":\"media\",\"details\":{\"title\":\"\",\"description\":\"\",\"id\":\"gzFMf4-iN9\",\"exampleContent\":null,\"instanceId\":\"U0gNOb557K\"},\"props\":{\"width\":{\"value\":100,\"unit\":\"%\"},\"height\":null,\"objectFit\":\"cover\",\"objectPositionX\":{\"value\":50,\"unit\":\"%\"},\"objectPositionY\":{\"value\":50,\"unit\":\"%\"}}} */ /* --- */  /* Type: spacing Id: GR8D2zPSUp Instance Id: U0gNOb557K */ .-spacing--[data-instance-id=\"U0gNOb557K\"]:not(._._._._._._#_) { padding-top: 0px; padding-right: 0px; padding-bottom: 0px; padding-left: 0px; ---spacing--row-gap: 0px; ---spacing--column-gap: 0px; } .-spacing--[data-instance-id=\"U0gNOb557K\"] > *:not(._._._._._._#_) { ---layout--row-gap: 0px; ---layout--column-gap: 0px; } /* Data: {\"type\":\"spacing\",\"details\":{\"title\":\"\",\"description\":\"\",\"id\":\"GR8D2zPSUp\",\"exampleContent\":null,\"instanceId\":\"U0gNOb557K\"},\"props\":{\"paddingTop\":{\"value\":0,\"unit\":\"px\"},\"paddingBottom\":{\"value\":0,\"unit\":\"px\"},\"paddingLeft\":{\"value\":0,\"unit\":\"px\"},\"paddingRight\":{\"value\":0,\"unit\":\"px\"},\"rowGap\":{\"value\":0,\"unit\":\"px\"},\"columnGap\":{\"value\":0,\"unit\":\"px\"}}} */ /* --- */  /* Type: spacing Id: 1Pbz5auvuy Title: Large section Instance Id: BMgDPUl8nx */ .-spacing--large-section[data-instance-id=\"BMgDPUl8nx\"]:not(._._._._._._#_) { padding-top: 8px; padding-right: 100px; padding-bottom: 8px; padding-left: 100px; ---spacing--row-gap: 12px; ---spacing--column-gap: 12px; } .-spacing--large-section[data-instance-id=\"BMgDPUl8nx\"] > *:not(._._._._._._#_) { ---layout--row-gap: 12px; ---layout--column-gap: 12px; } /* Data: {\"type\":\"spacing\",\"details\":{\"title\":\"Large section\",\"description\":\"\",\"id\":\"1Pbz5auvuy\",\"exampleContent\":null,\"slug\":\"large-section\",\"collectionId\":\"9zpuzADm9w\",\"instanceId\":\"BMgDPUl8nx\"},\"props\":{\"paddingTop\":{\"value\":8,\"unit\":\"px\"},\"paddingBottom\":{\"value\":8,\"unit\":\"px\"},\"paddingLeft\":{\"value\":100,\"unit\":\"px\"},\"paddingRight\":{\"value\":100,\"unit\":\"px\"},\"rowGap\":{\"value\":12,\"unit\":\"px\"},\"columnGap\":{\"value\":12,\"unit\":\"px\"}}} */ /* --- */  /* Type: dimensions Id: MeLzpwe4xn Instance Id: BMgDPUl8nx */ .-dimensions--[data-instance-id=\"BMgDPUl8nx\"]:not(._._._._._._#_) { max-width: min(var(---self--max-available-width, 100%), var(---self--max-width, 100%)); } /* Data: {\"type\":\"dimensions\",\"details\":{\"title\":\"\",\"description\":\"\",\"id\":\"MeLzpwe4xn\",\"exampleContent\":null,\"instanceId\":\"BMgDPUl8nx\"},\"props\":{\"minWidth\":null,\"maxWidth\":null,\"minHeight\":null,\"maxHeight\":null}} */</style><section class=\"-dimensions-- -grid--custom -spacing--large-section\" data-instance-id=\"BMgDPUl8nx\"><div class=\"-block--media -media-- -spacing--\" data-instance-id=\"U0gNOb557K\"><picture class=\"-image--foreground\"><img src=\"https://feaas.blob.core.windows.net/images/w5KOvtvgQFSL2hiaZ5mpxwSam-fgnb9D.png\" /></picture></div></section>",
    "diff": {},
    "breakpointIds": null,
    "datasourceIds": [],
    "isEmbeddable": false,
    "forkOriginId": null,
    "forkOriginRevision": 0,
    "forkedAt": null,
    "classList": [
      "-theme--default"
    ],
    "createdAt": "2024-06-26T03:10:54.728Z",
    "deletedAt": null,
    "modifiedAt": "2024-06-26T03:20:40.119Z",
    "modifiedBy": {
      "id": "63f775b550477258a136da0e",
      "name": "Christopher Haddad",
      "givenName": "Christopher",
      "familyName": "Haddad",
      "email": "chris.haddad@sitecore.com",
      "picture": "https://s.gravatar.com/avatar/a9f8fbaf23e64731b5291cfa9e8749d4?s=480&r=pg&d=https%3A%2F%2Fcdn.auth0.com%2Favatars%2Fch.png"
    }
  },
  {
    "libraryId": "generated",
    "id": "BzY8BHdnJy",
    "componentId": "RuLJJhsLkK",
    "name": "Name",
    "description": "",
    "status": "saved",
    "orderIdx": "03qKK",
    "revision": 17,
    "model": "",
    "view": "<style data-format-version=\"30\">/* Type: grid Id: custom-grid Title: Custom grid Instance Id: BMgDPUl8nx */ .-grid--custom[data-instance-id=\"BMgDPUl8nx\"]:not(._._._._._._#_) { ---self--display: grid; display: var(---self--display); grid-template-rows: minmax(36px,36px) minmax(36px,36px) minmax(36px,36px) minmax(36px,36px) minmax(36px, auto); grid-template-columns: minmax(0px,1fr) minmax(0px,1fr) minmax(0px,1fr) minmax(0px,1fr) minmax(0px,1fr) minmax(0px,1fr) minmax(0px,1fr) minmax(0px,1fr) minmax(0px,1fr) minmax(0px,1fr) minmax(0px,1fr) minmax(0px,1fr); row-gap: var(---spacing--row-gap); column-gap: var(---spacing--column-gap); } .-grid--custom[data-instance-id=\"BMgDPUl8nx\"] > :nth-child(1):not(._._._._._._#_) { grid-column: 1; grid-column-end: 13; grid-row: 1; grid-row-end: 6; order: 0; position: relative; } /* Data: {\"type\":\"grid\",\"details\":{\"title\":\"Custom grid\",\"description\":\"\",\"id\":\"custom-grid\",\"exampleContent\":null,\"slug\":\"custom\",\"isInternal\":true,\"isHidden\":true,\"instanceId\":\"BMgDPUl8nx\"},\"props\":{\"columns\":[{\"min\":{\"value\":0,\"unit\":\"px\"},\"max\":{\"value\":1,\"unit\":\"fr\"}},{\"min\":{\"value\":0,\"unit\":\"px\"},\"max\":{\"value\":1,\"unit\":\"fr\"}},{\"min\":{\"value\":0,\"unit\":\"px\"},\"max\":{\"value\":1,\"unit\":\"fr\"}},{\"min\":{\"value\":0,\"unit\":\"px\"},\"max\":{\"value\":1,\"unit\":\"fr\"}},{\"min\":{\"value\":0,\"unit\":\"px\"},\"max\":{\"value\":1,\"unit\":\"fr\"}},{\"min\":{\"value\":0,\"unit\":\"px\"},\"max\":{\"value\":1,\"unit\":\"fr\"}},{\"min\":{\"value\":0,\"unit\":\"px\"},\"max\":{\"value\":1,\"unit\":\"fr\"}},{\"min\":{\"value\":0,\"unit\":\"px\"},\"max\":{\"value\":1,\"unit\":\"fr\"}},{\"min\":{\"value\":0,\"unit\":\"px\"},\"max\":{\"value\":1,\"unit\":\"fr\"}},{\"min\":{\"value\":0,\"unit\":\"px\"},\"max\":{\"value\":1,\"unit\":\"fr\"}},{\"min\":{\"value\":0,\"unit\":\"px\"},\"max\":{\"value\":1,\"unit\":\"fr\"}},{\"min\":{\"value\":0,\"unit\":\"px\"},\"max\":{\"value\":1,\"unit\":\"fr\"}}],\"rows\":[{\"min\":{\"value\":36,\"unit\":\"px\"},\"max\":{\"value\":36,\"unit\":\"px\"}},{\"min\":{\"value\":36,\"unit\":\"px\"},\"max\":{\"value\":36,\"unit\":\"px\"}},{\"min\":{\"value\":36,\"unit\":\"px\"},\"max\":{\"value\":36,\"unit\":\"px\"}},{\"min\":{\"value\":36,\"unit\":\"px\"},\"max\":{\"value\":36,\"unit\":\"px\"}},{\"min\":{\"value\":36,\"unit\":\"px\"},\"max\":null}],\"items\":[{\"from\":{\"row\":1,\"column\":1},\"to\":{\"row\":6,\"column\":13},\"order\":0}]}} */ /* --- */  /* Type: media Id: gzFMf4-iN9 Instance Id: U0gNOb557K */ .-media--[data-instance-id=\"U0gNOb557K\"][class*=\"-block--media\"]:not(._._._._._._#_) { width: 100%; } .-media--[data-instance-id=\"U0gNOb557K\"] > picture:not(._._._._._._#_) { position: relative; overflow: hidden; height: auto; } .-media--[data-instance-id=\"U0gNOb557K\"] > picture > img:not(._._._._._._#_) { object-fit: cover; object-position: 50% 50%; } /* Data: {\"type\":\"media\",\"details\":{\"title\":\"\",\"description\":\"\",\"id\":\"gzFMf4-iN9\",\"exampleContent\":null,\"instanceId\":\"U0gNOb557K\"},\"props\":{\"width\":{\"value\":100,\"unit\":\"%\"},\"height\":null,\"objectFit\":\"cover\",\"objectPositionX\":{\"value\":50,\"unit\":\"%\"},\"objectPositionY\":{\"value\":50,\"unit\":\"%\"}}} */ /* --- */  /* Type: spacing Id: GR8D2zPSUp Instance Id: U0gNOb557K */ .-spacing--[data-instance-id=\"U0gNOb557K\"]:not(._._._._._._#_) { padding-top: 0px; padding-right: 0px; padding-bottom: 0px; padding-left: 0px; ---spacing--row-gap: 0px; ---spacing--column-gap: 0px; } .-spacing--[data-instance-id=\"U0gNOb557K\"] > *:not(._._._._._._#_) { ---layout--row-gap: 0px; ---layout--column-gap: 0px; } /* Data: {\"type\":\"spacing\",\"details\":{\"title\":\"\",\"description\":\"\",\"id\":\"GR8D2zPSUp\",\"exampleContent\":null,\"instanceId\":\"U0gNOb557K\"},\"props\":{\"paddingTop\":{\"value\":0,\"unit\":\"px\"},\"paddingBottom\":{\"value\":0,\"unit\":\"px\"},\"paddingLeft\":{\"value\":0,\"unit\":\"px\"},\"paddingRight\":{\"value\":0,\"unit\":\"px\"},\"rowGap\":{\"value\":0,\"unit\":\"px\"},\"columnGap\":{\"value\":0,\"unit\":\"px\"}}} */ /* --- */  /* Type: spacing Id: 1Pbz5auvuy Title: Large section Instance Id: BMgDPUl8nx */ .-spacing--large-section[data-instance-id=\"BMgDPUl8nx\"]:not(._._._._._._#_) { padding-top: 8px; padding-right: 100px; padding-bottom: 8px; padding-left: 100px; ---spacing--row-gap: 12px; ---spacing--column-gap: 12px; } .-spacing--large-section[data-instance-id=\"BMgDPUl8nx\"] > *:not(._._._._._._#_) { ---layout--row-gap: 12px; ---layout--column-gap: 12px; } /* Data: {\"type\":\"spacing\",\"details\":{\"title\":\"Large section\",\"description\":\"\",\"id\":\"1Pbz5auvuy\",\"exampleContent\":null,\"slug\":\"large-section\",\"collectionId\":\"9zpuzADm9w\",\"instanceId\":\"BMgDPUl8nx\"},\"props\":{\"paddingTop\":{\"value\":8,\"unit\":\"px\"},\"paddingBottom\":{\"value\":8,\"unit\":\"px\"},\"paddingLeft\":{\"value\":100,\"unit\":\"px\"},\"paddingRight\":{\"value\":100,\"unit\":\"px\"},\"rowGap\":{\"value\":12,\"unit\":\"px\"},\"columnGap\":{\"value\":12,\"unit\":\"px\"}}} */ /* --- */  /* Type: dimensions Id: MeLzpwe4xn Instance Id: BMgDPUl8nx */ .-dimensions--[data-instance-id=\"BMgDPUl8nx\"]:not(._._._._._._#_) { max-width: min(var(---self--max-available-width, 100%), var(---self--max-width, 100%)); } /* Data: {\"type\":\"dimensions\",\"details\":{\"title\":\"\",\"description\":\"\",\"id\":\"MeLzpwe4xn\",\"exampleContent\":null,\"instanceId\":\"BMgDPUl8nx\"},\"props\":{\"minWidth\":null,\"maxWidth\":null,\"minHeight\":null,\"maxHeight\":null}} */</style><section class=\"-dimensions-- -grid--custom -spacing--large-section\" data-instance-id=\"BMgDPUl8nx\"><div class=\"-block--media -media-- -spacing--\" data-instance-id=\"U0gNOb557K\"><picture class=\"-image--foreground\"><img src=\"https://feaas.blob.core.windows.net/images/w5KOvtvgQFSL2hiaZ5mpxwSam-fgnb9D.png\" /></picture></div></section>",
    "diff": {},
    "breakpointIds": null,
    "datasourceIds": [],
    "isEmbeddable": false,
    "forkOriginId": null,
    "forkOriginRevision": 0,
    "forkedAt": null,
    "classList": [
      "-theme--default"
    ],
    "createdAt": "2024-06-26T03:10:54.728Z",
    "deletedAt": null,
    "modifiedAt": "2024-06-26T03:20:40.119Z",
    "modifiedBy": {
      "id": "63f775b550477258a136da0e",
      "name": "Christopher Haddad",
      "givenName": "Christopher",
      "familyName": "Haddad",
      "email": "chris.haddad@sitecore.com",
      "picture": "https://s.gravatar.com/avatar/a9f8fbaf23e64731b5291cfa9e8749d4?s=480&r=pg&d=https%3A%2F%2Fcdn.auth0.com%2Favatars%2Fch.png"
    }
  }
]
